symboliq/__init__.py
symboliq/_version.py
symboliq/_version_test.py
symboliq/dirac_notation.py
symboliq/dirac_notation_test.py
symboliq-0.0.2.dist-info/LICENSE
symboliq-0.0.2.dist-info/METADATA
symboliq-0.0.2.dist-info/WHEEL
symboliq-0.0.2.dist-info/top_level.txt
symboliq-0.0.2.dist-info/RECORD
