Metadata-Version: 2.1
Name: symboliq
Version: 0.0.2
Summary: SymboliQ is a python framework for Symbolic Quantum computation
Home-page: https://github.com/SupertechLabs/SymboliQ
Author: Victory Omole
Author-email: vtomole2@gmail.com
License: Apache 2
Requires-Python: >=3.8.0
License-File: LICENSE
Requires-Dist: sympy
Provides-Extra: dev
Requires-Dist: general-superstaq[dev] (~=0.3.9) ; extra == 'dev'
